[
  {
    "title": "Senior Software Development Expert",
    "company": "enspired",
    "logo_url": "/assets/images/sponsors/enspired.png",
    "location": "Vienna, Austria",
    "apply_url": "https://enspired.recruitee.com/o/senior-software-development-expert-fmx-3?source=WTM"
  },
  {
    "title": "Senior Algorithm Development Expert",
    "company": "enspired",
    "logo_url": "/assets/images/sponsors/enspired.png",
    "location": "Vienna, Austria",
    "apply_url": "https://enspired.recruitee.com/o/senior-algorithm-development-expert-fmx?source=WTM"
  },
  {
    "title": "Senior Cloud Operations Expert",
    "company": "enspired",
    "logo_url": "/assets/images/sponsors/enspired.png",
    "location": "Vienna, Austria",
    "apply_url": "https://enspired.recruitee.com/o/senior-cloud-operations-expert-mfx?source=WTM"
  }
]